tic_tac_game/__init__.py
tic_tac_game-0.0.1.dist-info/LICENSE.MIT
tic_tac_game-0.0.1.dist-info/METADATA
tic_tac_game-0.0.1.dist-info/WHEEL
tic_tac_game-0.0.1.dist-info/top_level.txt
tic_tac_game-0.0.1.dist-info/RECORD
