Metadata-Version: 2.1
Name: tic-tac-game
Version: 0.0.1
Summary: A sample test package
Home-page: https://github.com/BehruzYBF/tic_tac_game
Author: Bekhruz
Author-email: iutstudent2022@gmail.com
License: MIT
Requires-Python: >=3.8
License-File: LICENSE.MIT
